apklisparser/__init__.py
apklisparser/apk.py
apklisparser/build_icon.py
apklisparser/vd2png.py
apklisparser-1.1.0.dist-info/METADATA
apklisparser-1.1.0.dist-info/WHEEL
apklisparser-1.1.0.dist-info/top_level.txt
apklisparser-1.1.0.dist-info/RECORD
