Metadata-Version: 2.4
Name: apklisparser
Version: 1.1.0
Summary: Apklis apk parser
Home-page: https://github.com/ramendoza/apklisparser
Author: Rafael Mendoza
Author-email: ralexm14@gmail.com
Requires-Python: >=3.9
Requires-Dist: androguard
Requires-Dist: wand
Dynamic: author
Dynamic: author-email
Dynamic: description
Dynamic: description-content-type
Dynamic: home-page
Dynamic: requires-dist
Dynamic: requires-python
Dynamic: summary
